{"Activeongoogleplay": 0, "Error": false, "Status": 1, "Message": "Auth token successfully matched", "Payload": [{"id": 1333, "subject_id": 28, "video_title": "1. Neoplasia (59:44)", "video_category_id": 84, "video_category": "5. Neoplasia (5.5 Hrs)", "video_url": "https://www.youtube.com/watch?v=4--IPrGDI3w", "video_image_url": "https://i.ytimg.com/vi/4--IPrGDI3w/hqdefault.jpg", "video_type": 0, "video_length": "00:59:43", "notes": "16013656155f72e66fcc884.pdf", "video_order": 0, "status": 1, "date": "2019-12-23", "avg_rating": 5, "user_rating": 0}, {"id": 1334, "subject_id": 28, "video_title": "2. Hallmark of Cancer Cells (44:04)", "video_category_id": 84, "video_category": "5. Neoplasia (5.5 Hrs)", "video_url": "https://www.youtube.com/watch?v=22lNSCs14kY", "video_image_url": "https://i.ytimg.com/vi/22lNSCs14kY/hqdefault.jpg", "video_type": 0, "video_length": "00:44:03", "notes": "16013657665f72e706921fe.pdf", "video_order": 1, "status": 1, "date": "2019-12-23", "avg_rating": 5, "user_rating": 0}, {"id": 1335, "subject_id": 28, "video_title": "3. Genes and Protooncogenes (1:17:16)", "video_category_id": 84, "video_category": "5. Neoplasia (5.5 Hrs)", "video_url": "https://www.youtube.com/watch?v=imnvtqvehPM", "video_image_url": "https://i.ytimg.com/vi/imnvtqvehPM/hqdefault.jpg", "video_type": 0, "video_length": "01:17:15", "notes": "16013658085f72e7305128c.pdf", "video_order": 2, "status": 1, "date": "2019-12-23", "avg_rating": 5, "user_rating": 0}, {"id": 1336, "subject_id": 28, "video_title": "4. Tumor Suppressors (40:40)", "video_category_id": 84, "video_category": "5. Neoplasia (5.5 Hrs)", "video_url": "https://www.youtube.com/watch?v=rkG3VNSh6sQ", "video_image_url": "https://i.ytimg.com/vi/rkG3VNSh6sQ/hqdefault.jpg", "video_type": 0, "video_length": "00:40:39", "notes": "16013658275f72e7432ef5c.pdf", "video_order": 3, "status": 1, "date": "2019-12-23", "avg_rating": 5, "user_rating": 0}, {"id": 1337, "subject_id": 28, "video_title": "5. Various Carcinogenesis (37:22)", "video_category_id": 84, "video_category": "5. Neoplasia (5.5 Hrs)", "video_url": "https://www.youtube.com/watch?v=n3gYF_BG2gM", "video_image_url": "https://i.ytimg.com/vi/n3gYF_BG2gM/hqdefault.jpg", "video_type": 0, "video_length": "00:37:20", "notes": "16013658775f72e775a0fdf.pdf", "video_order": 4, "status": 1, "date": "2019-12-23", "avg_rating": 5, "user_rating": 0}, {"id": 1338, "subject_id": 28, "video_title": "6. Approach towards Tumor Diagnosis Part 01 (31:38)", "video_category_id": 84, "video_category": "5. Neoplasia (5.5 Hrs)", "video_url": "https://www.youtube.com/watch?v=qBqW9x9Pqig", "video_image_url": "https://i.ytimg.com/vi/qBqW9x9Pqig/hqdefault.jpg", "video_type": 0, "video_length": "00:31:37", "notes": "16013658985f72e78a22436.pdf", "video_order": 5, "status": 1, "date": "2019-12-23", "avg_rating": 5, "user_rating": 0}, {"id": 1339, "subject_id": 28, "video_title": "7. Approach towards Tumor Diagnosis Part 02 (50:29)", "video_category_id": 84, "video_category": "5. Neoplasia (5.5 Hrs)", "video_url": "https://www.youtube.com/watch?v=hTk55HdIQK0", "video_image_url": "https://i.ytimg.com/vi/hTk55HdIQK0/hqdefault.jpg", "video_type": 0, "video_length": "00:50:28", "notes": "16013669205f72eb88e9268.pdf", "video_order": 6, "status": 1, "date": "2019-12-23", "avg_rating": 5, "user_rating": 0}]}